pycoustic/__init__.py
pycoustic/log.py
pycoustic/pycoustic_gui_app.py
pycoustic/survey.py
pycoustic/tkgui.py
pycoustic/weather.py
pycoustic-0.1.17.dist-info/METADATA
pycoustic-0.1.17.dist-info/WHEEL
pycoustic-0.1.17.dist-info/RECORD
