Metadata-Version: 2.3
Name: pycoustic
Version: 0.1.17
Summary: 
Author: thumpercastle
Author-email: tony.ryb@gmail.com
Requires-Python: >=3.11,<=3.13
Classifier: Programming Language :: Python :: 3
Classifier: Programming Language :: Python :: 3.11
Classifier: Programming Language :: Python :: 3.12
Classifier: Programming Language :: Python :: 3.13
Requires-Dist: numpy (==2.3.3)
Requires-Dist: openpyxl (==3.1.5)
Requires-Dist: pandas (==2.3.3)
Requires-Dist: plotly (>=6.3.1,<7.0.0)
Requires-Dist: requests (>=2.32.4,<3.0.0)
Requires-Dist: streamlit (>=1.46.1,<2.0.0)
